{
  "entry": "server.js",
  "files": {
    "1333e15d64b23bcc8638.js": "1333e15d64b23bcc8638.js",
    "178d17828aa0075ac702.js": "178d17828aa0075ac702.js",
    "7bbda967e196bfc78b87.js": "7bbda967e196bfc78b87.js",
    "9eac8dc3acbf320c14d3.js": "9eac8dc3acbf320c14d3.js",
    "server.js": "server.js"
  },
  "maps": {
    "1333e15d64b23bcc8638.js": "1333e15d64b23bcc8638.js.map",
    "178d17828aa0075ac702.js": "178d17828aa0075ac702.js.map",
    "7bbda967e196bfc78b87.js": "7bbda967e196bfc78b87.js.map",
    "9eac8dc3acbf320c14d3.js": "9eac8dc3acbf320c14d3.js.map",
    "server.js": "server.js.map"
  }
}